doctorr/__init__.py
doctorr/__main__.py
doctorr/cli.py
doctorr/include.py
doctorr/parse_config.py
doctorr/templates.py
doctorr/utils.py
doctorr/watchmode.py
doctorr/autocli/__init__.py
doctorr/autocli/__main__.py
doctorr/autocli/inspection.py
doctorr/autocli/parse_argparse.py
doctorr/autocli/parse_config.py
doctorr/autocli/run.py
doctorr/autocli/templates.py
doctorr/autodoc/__init__.py
doctorr/autodoc/docstring.py
doctorr/autodoc/inspection.py
doctorr/autodoc/parse_config.py
doctorr/autodoc/run.py
doctorr/autodoc/templates.py
doctorr/templates/themes/md_basic/class.jinja2
doctorr/templates/themes/md_basic/cli.jinja2
doctorr/templates/themes/md_basic/docstring.jinja2
doctorr/templates/themes/md_basic/function.jinja2
doctorr/templates/themes/md_basic/method.jinja2
doctorr/templates/themes/md_basic/page.jinja2
doctorr/templates/themes/md_basic/property.jinja2
doctorr/templates/themes/nuxt_content/class.jinja2
doctorr/templates/themes/nuxt_content/cli.jinja2
doctorr/templates/themes/nuxt_content/docstring.jinja2
doctorr/templates/themes/nuxt_content/function.jinja2
doctorr/templates/themes/nuxt_content/method.jinja2
doctorr/templates/themes/nuxt_content/page.jinja2
doctorr/templates/themes/nuxt_content/property.jinja2
doctorr-0.1.7.dist-info/LICENSE
doctorr-0.1.7.dist-info/METADATA
doctorr-0.1.7.dist-info/WHEEL
doctorr-0.1.7.dist-info/top_level.txt
doctorr-0.1.7.dist-info/RECORD
