Metadata-Version: 2.1
Name: doctorr
Version: 0.1.7
Summary: Next level flexible autodocumentation tooling for python pros.
Author: Rémi CONNESSON
License-File: LICENSE
Requires-Dist: pyyaml
Requires-Dist: jinja2
Requires-Dist: watchdog
